[
    {
        "Material":"Couro",
        "Tier":"Tier 1",
        "Tipo":"Base",
        "Elemento":"x",
        "Preço Base":"10",
        "Drop":"Monstro",
        "Drop Rate Base":"",
        "CR Mínimo":"",
        "Quantidade":""
    },
    {
        "Material":"Ferro",
        "Tier":"Tier 1",
        "Tipo":"Base",
        "Elemento":"x",
        "Preço Base":"10",
        "Drop":"Mundo",
        "Drop Rate Base":"",
        "CR Mínimo":"",
        "Quantidade":""
    },
    {
        "Material":"Madeira",
        "Tier":"Tier 1",
        "Tipo":"Base",
        "Elemento":"x",
        "Preço Base":"10",
        "Drop":"Mundo",
        "Drop Rate Base":"",
        "CR Mínimo":"",
        "Quantidade":""
    },
    {
        "Material":"Cristal de Mana",
        "Tier":"Tier 1",
        "Tipo":"Essência",
        "Elemento":"x",
        "Preço Base":"50",
        "Drop":"Monstro",
        "Drop Rate Base":"35+(2xCR)%",
        "CR Mínimo":"1",
        "Quantidade":"Máximo: 4 por criatura (equilibre com CR)"
    },
    {
        "Material":"Granadita Ardente",
        "Tier":"Tier 1",
        "Tipo":"Essência",
        "Elemento":"FIre",
        "Preço Base":"700",
        "Drop":"Monstro",
        "Drop Rate Base":"20+CR%",
        "CR Mínimo":"4",
        "Quantidade":"Máximo: 2 por criatura (acima de CR8)"
    },
    {
        "Material":"Turmalina Gélida",
        "Tier":"Tier 1",
        "Tipo":"Essência",
        "Elemento":"Cold",
        "Preço Base":"700",
        "Drop":"Monstro",
        "Drop Rate Base":"20+CR%",
        "CR Mínimo":"4",
        "Quantidade":"Máximo: 2 por criatura (acima de CR8)"
    },
    {
        "Material":"Topázio Voltáico",
        "Tier":"Tier 1",
        "Tipo":"Essência",
        "Elemento":"Lightning",
        "Preço Base":"700",
        "Drop":"Monstro",
        "Drop Rate Base":"20+CR%",
        "CR Mínimo":"4",
        "Quantidade":"Máximo: 2 por criatura (acima de CR8)"
    },
    {
        "Material":"Malaquita Corrosiva",
        "Tier":"Tier 1",
        "Tipo":"Essência",
        "Elemento":"Acid",
        "Preço Base":"700",
        "Drop":"Monstro",
        "Drop Rate Base":"20+CR%",
        "CR Mínimo":"4",
        "Quantidade":"Máximo: 2 por criatura (acima de CR8)"
    },
    {
        "Material":"Jade Virulenta",
        "Tier":"Tier 1",
        "Tipo":"Essência",
        "Elemento":"Poison",
        "Preço Base":"700",
        "Drop":"Monstro",
        "Drop Rate Base":"20+CR%",
        "CR Mínimo":"4",
        "Quantidade":"Máximo: 2 por criatura (acima de CR8)"
    },
    {
        "Material":"Ônix Crepuscular",
        "Tier":"Tier 1",
        "Tipo":"Essência",
        "Elemento":"Necrotic",
        "Preço Base":"700",
        "Drop":"Monstro",
        "Drop Rate Base":"20+CR%",
        "CR Mínimo":"4",
        "Quantidade":"Máximo: 2 por criatura (acima de CR8)"
    },
    {
        "Material":"Diamante Celeste",
        "Tier":"Tier 1",
        "Tipo":"Essência",
        "Elemento":"Radiant",
        "Preço Base":"700",
        "Drop":"Monstro",
        "Drop Rate Base":"20+CR%",
        "CR Mínimo":"4",
        "Quantidade":"Máximo: 2 por criatura (acima de CR8)"
    },
    {
        "Material":"Quartzo Sísmico",
        "Tier":"Tier 1",
        "Tipo":"Essência",
        "Elemento":"Force",
        "Preço Base":"700",
        "Drop":"Monstro",
        "Drop Rate Base":"20+CR%",
        "CR Mínimo":"4",
        "Quantidade":"Máximo: 2 por criatura (acima de CR8)"
    },
    {
        "Material":"Ametista Clairvoyante",
        "Tier":"Tier 1",
        "Tipo":"Essência",
        "Elemento":"Psíquico",
        "Preço Base":"700",
        "Drop":"Monstro",
        "Drop Rate Base":"20+CR%",
        "CR Mínimo":"4",
        "Quantidade":"Máximo: 2 por criatura (acima de CR8)"
    },
    {
        "Material":"Cristal Ressonante",
        "Tier":"Tier 1",
        "Tipo":"Essência",
        "Elemento":"Thunder",
        "Preço Base":"700",
        "Drop":"Monstro",
        "Drop Rate Base":"20+CR%",
        "CR Mínimo":"4",
        "Quantidade":"Máximo: 2 por criatura (acima de CR8)"
    },
    {
        "Material":"Âmbar Vivo",
        "Tier":"Tier 1",
        "Tipo":"Essência",
        "Elemento":"Heal",
        "Preço Base":"700",
        "Drop":"Monstro",
        "Drop Rate Base":"20+CR%",
        "CR Mínimo":"4",
        "Quantidade":"Máximo: 2 por criatura (acima de CR8)"
    },
    {
        "Material":"Couro Trabalhado",
        "Tier":"Tier 2",
        "Tipo":"Base",
        "Elemento":"x",
        "Preço Base":"50",
        "Drop":"Monstro",
        "Drop Rate Base":"100%",
        "CR Mínimo":"",
        "Quantidade":""
    },
    {
        "Material":"Aço",
        "Tier":"Tier 2",
        "Tipo":"Base",
        "Elemento":"x",
        "Preço Base":"50",
        "Drop":"Mundo",
        "Drop Rate Base":"",
        "CR Mínimo":"",
        "Quantidade":""
    },
    {
        "Material":"Madeira-de-Lei",
        "Tier":"Tier 2",
        "Tipo":"Base",
        "Elemento":"x",
        "Preço Base":"50",
        "Drop":"Mundo",
        "Drop Rate Base":"",
        "CR Mínimo":"",
        "Quantidade":""
    },
    {
        "Material":"Aetherium",
        "Tier":"Tier 2",
        "Tipo":"Essência",
        "Elemento":"x",
        "Preço Base":"200",
        "Drop":"Monstro",
        "Drop Rate Base":"20+CR%",
        "CR Mínimo":"10",
        "Quantidade":""
    },
    {
        "Material":"Ignita",
        "Tier":"Tier 2",
        "Tipo":"Essência",
        "Elemento":"Fire",
        "Preço Base":"2100",
        "Drop":"Monstro",
        "Drop Rate Base":"10+(1\/2CR)%",
        "CR Mínimo":"15",
        "Quantidade":"Máximo: 1"
    },
    {
        "Material":"Aquamarita",
        "Tier":"Tier 2",
        "Tipo":"Essência",
        "Elemento":"Cold",
        "Preço Base":"2100",
        "Drop":"Monstro",
        "Drop Rate Base":"10+(1\/2CR)%",
        "CR Mínimo":"15",
        "Quantidade":"Máximo: 1"
    },
    {
        "Material":"Fulgorita",
        "Tier":"Tier 2",
        "Tipo":"Essência",
        "Elemento":"Lightning",
        "Preço Base":"2100",
        "Drop":"Monstro",
        "Drop Rate Base":"10+(1\/2CR)%",
        "CR Mínimo":"15",
        "Quantidade":"Máximo: 1"
    },
    {
        "Material":"Ácidalita",
        "Tier":"Tier 2",
        "Tipo":"Essência",
        "Elemento":"Acid",
        "Preço Base":"2100",
        "Drop":"Monstro",
        "Drop Rate Base":"10+(1\/2CR)%",
        "CR Mínimo":"15",
        "Quantidade":"Máximo: 1"
    },
    {
        "Material":"Serpetinita",
        "Tier":"Tier 2",
        "Tipo":"Essência",
        "Elemento":"Poison",
        "Preço Base":"2100",
        "Drop":"Monstro",
        "Drop Rate Base":"10+(1\/2CR)%",
        "CR Mínimo":"15",
        "Quantidade":"Máximo: 1"
    },
    {
        "Material":"Obsidianyx",
        "Tier":"Tier 2",
        "Tipo":"Essência",
        "Elemento":"Necrotic",
        "Preço Base":"2100",
        "Drop":"Monstro",
        "Drop Rate Base":"10+(1\/2CR)%",
        "CR Mínimo":"15",
        "Quantidade":"Máximo: 1"
    },
    {
        "Material":"Aurorita",
        "Tier":"Tier 2",
        "Tipo":"Essência",
        "Elemento":"Radiant",
        "Preço Base":"2100",
        "Drop":"Monstro",
        "Drop Rate Base":"10+(1\/2CR)%",
        "CR Mínimo":"15",
        "Quantidade":"Máximo: 1"
    },
    {
        "Material":"Tremorita",
        "Tier":"Tier 2",
        "Tipo":"Essência",
        "Elemento":"Force",
        "Preço Base":"2100",
        "Drop":"Monstro",
        "Drop Rate Base":"10+(1\/2CR)%",
        "CR Mínimo":"15",
        "Quantidade":"Máximo: 1"
    },
    {
        "Material":"Psicalita",
        "Tier":"Tier 2",
        "Tipo":"Essência",
        "Elemento":"Psíquico",
        "Preço Base":"2100",
        "Drop":"Monstro",
        "Drop Rate Base":"10+(1\/2CR)%",
        "CR Mínimo":"15",
        "Quantidade":"Máximo: 1"
    },
    {
        "Material":"Ecoita",
        "Tier":"Tier 2",
        "Tipo":"Essência",
        "Elemento":"Thunder",
        "Preço Base":"2100",
        "Drop":"Monstro",
        "Drop Rate Base":"10+(1\/2CR)%",
        "CR Mínimo":"15",
        "Quantidade":"Máximo: 1"
    },
    {
        "Material":"Espectrolita",
        "Tier":"Tier 2",
        "Tipo":"Essência",
        "Elemento":"Heal",
        "Preço Base":"2100",
        "Drop":"Monstro",
        "Drop Rate Base":"10+(1\/2CR)%",
        "CR Mínimo":"15",
        "Quantidade":"Máximo: 1"
    }
]